Metadata-Version: 1.0
Name: p4f
Version: 0.0.12
Summary: pwntools helper
Home-page: http://github.com
Author: Msk
Author-email: moskong@qq.com
License: MIT
Platform: UNKNOWN
